sonarqube/__init__.py
sonarqube/api.py
sonarqube/cli.py
sonarqube/community.py
sonarqube/exceptions.py
sonarqube/parser.py
sonarqube/utils.py
sonarqube_py-0.7.0.dist-info/LICENSE
sonarqube_py-0.7.0.dist-info/METADATA
sonarqube_py-0.7.0.dist-info/WHEEL
sonarqube_py-0.7.0.dist-info/RECORD
